wagtail_shell/__init__.py
wagtail_shell/apps.py
wagtail_shell/decorators.py
wagtail_shell/menu.py
wagtail_shell/response.py
wagtail_shell/wagtail_hooks.py
wagtail_shell/migrations/__init__.py
wagtail_shell/static/wagtail_shell/fonts/.gitignore
wagtail_shell/static/wagtail_shell/fonts/opensans-bold.woff
wagtail_shell/static/wagtail_shell/fonts/opensans-bold.woff2
wagtail_shell/static/wagtail_shell/fonts/opensans-light.woff
wagtail_shell/static/wagtail_shell/fonts/opensans-light.woff2
wagtail_shell/static/wagtail_shell/fonts/opensans-regular.woff
wagtail_shell/static/wagtail_shell/fonts/opensans-regular.woff2
wagtail_shell/static/wagtail_shell/fonts/opensans-semibold.woff
wagtail_shell/static/wagtail_shell/fonts/opensans-semibold.woff2
wagtail_shell/static/wagtail_shell/fonts/robotoslab-bold.woff
wagtail_shell/static/wagtail_shell/fonts/robotoslab-bold.woff2
wagtail_shell/static/wagtail_shell/fonts/robotoslab-regular.woff
wagtail_shell/static/wagtail_shell/fonts/robotoslab-regular.woff2
wagtail_shell/static/wagtail_shell/fonts/wagtail.woff
wagtail_shell/static/wagtail_shell/images/.gitignore
wagtail_shell/static/wagtail_shell/js/.gitignore
wagtail_shell/static/wagtail_shell/js/wagtail-shell.js
wagtail_shell/static_src/custom.d.ts
wagtail_shell/static_src/fetch.ts
wagtail_shell/static_src/main.tsx
wagtail_shell/static_src/navigation.ts
wagtail_shell/static_src/components/Browser.tsx
wagtail_shell/static_src/components/Frame.tsx
wagtail_shell/static_src/components/Logo.tsx
wagtail_shell/static_src/components/Menu.tsx
wagtail_shell/static_src/components/ModalWindow.tsx
wagtail_shell/static_src/components/SearchInput.tsx
wagtail_shell/static_src/components/Sidebar.tsx
wagtail_shell/static_src/components/Explorer/Explorer.scss
wagtail_shell/static_src/components/Explorer/Explorer.tsx
wagtail_shell/static_src/components/Explorer/ExplorerHeader.tsx
wagtail_shell/static_src/components/Explorer/ExplorerItem.scss
wagtail_shell/static_src/components/Explorer/ExplorerItem.tsx
wagtail_shell-0.1.0.dist-info/LICENSE
wagtail_shell-0.1.0.dist-info/METADATA
wagtail_shell-0.1.0.dist-info/WHEEL
wagtail_shell-0.1.0.dist-info/top_level.txt
wagtail_shell-0.1.0.dist-info/RECORD
